epic_api_client/EPICClient.py
epic_api_client/EPICHttpClient.py
epic_api_client/EPICLib.py
epic_api_client/FHIRBase.py
epic_api_client/FHIRExtension.py
epic_api_client/JWTGenerator.py
epic_api_client/SimpleHttpClient.py
epic_api_client/__init__.py
epic_api_client-2025.1.12.dist-info/METADATA
epic_api_client-2025.1.12.dist-info/WHEEL
epic_api_client-2025.1.12.dist-info/top_level.txt
epic_api_client-2025.1.12.dist-info/RECORD
