Metadata-Version: 2.4
Name: epic-api-client
Version: 2025.1.12
Summary: EPIC API Client including authentication flow and some wrapped API calls
Author-email: Oscar van der Meer <o.m.vandermeer@amsterdamumc.nl>
Maintainer-email: Oscar van der Meer <o.m.vandermeer@amsterdamumc.nl>
Classifier: Programming Language :: Python :: 3
Classifier: License :: OSI Approved :: MIT License
Classifier: Operating System :: OS Independent
Requires-Python: >=3.8
Requires-Dist: requests
Requires-Dist: PyJWT
Requires-Dist: cryptography
Requires-Dist: uuid
Requires-Dist: requests_unixsocket
